rfhq/__init__.py
rfhq/decorators.py
rfhq/fields.py
rfhq/filters.py
rfhq/mixins.py
rfhq/parsers.py
rfhq/relations.py
rfhq/renderers.py
rfhq/routers.py
rfhq/serializers.py
rfhq/views.py
rfhq/elasticsearch/__init__.py
rfhq/elasticsearch/fields.py
rfhq/elasticsearch/filters.py
rfhq/elasticsearch/mixins.py
rfhq/elasticsearch/pagination.py
rfhq/elasticsearch/serializers.py
rfhq/elasticsearch/views.py
rfhq/pandas/__init__.py
rfhq/pandas/serializers.py
rfhq-0.1.17.dist-info/LICENSE
rfhq-0.1.17.dist-info/METADATA
rfhq-0.1.17.dist-info/WHEEL
rfhq-0.1.17.dist-info/top_level.txt
rfhq-0.1.17.dist-info/RECORD
