Metadata-Version: 2.1
Name: rfhq
Version: 0.1.17
Summary: UNKNOWN
Home-page: https://github.com/predicthq/rfhq
Author: PredictHQ
Author-email: developers@predicthq.com
License: MIT
Platform: UNKNOWN
Classifier: License :: OSI Approved :: MIT License
Classifier: Development Status :: 3 - Alpha
Classifier: Environment :: Web Environment
Classifier: Intended Audience :: Developers
Classifier: Operating System :: OS Independent
Classifier: Programming Language :: Python
Classifier: Programming Language :: Python :: 2
Classifier: Programming Language :: Python :: 2.7
Classifier: Programming Language :: Python :: 3
Classifier: Programming Language :: Python :: 3.4
Classifier: Programming Language :: Python :: 3.5
Classifier: Topic :: Software Development :: Libraries :: Python Modules
Classifier: Framework :: Django
Requires-Dist: Django (<=1.11,>=1.8)
Requires-Dist: djangorestframework (<3.10.0,>=3.1.3)
Requires-Dist: inflection
Requires-Dist: python-dateutil
Requires-Dist: elasticsearch (<2.0.0)
Requires-Dist: elasticsearch-dsl (<2.0.0)
